[
  {
    "question": "What is the name of Harry Potter's owl?",
    "options": [
      {
        "text": "Draco",
        "value": 0
      },
      {
        "text": "Hedwig",
        "value": 1
      },
      {
        "text": "Stephen",
        "value": 0
      },
      {
        "text": "Molly",
        "value": 0
      }
    ]
  },
  {
    "question": "Which actor played the character Cedric Diggory?",
    "options": [
      {
        "text": "Martin Bayfield",
        "value": 0
      },
      {
        "text": "Helena Bonham Carter",
        "value": 0
      },
      {
        "text": "Robert Pattinson",
        "value": 1
      },
      {
        "text": "Timothy Spall",
        "value": 0
      }
    ]
  }
]